Metadata-Version: 1.0
Name: default-argparse
Version: 0.0.1
Summary: The default command parser I always use.
Home-page: https://github.com/chrisnorman7/default_argparse.git
Author: UNKNOWN
Author-email: UNKNOWN
License: MPL-2
Platform: UNKNOWN
